yt_concate/__init__.py
yt_concate/main.py
yt_concate/settings.py
yt_concate/utils.py
yt_concate/models/__init__.py
yt_concate/models/found.py
yt_concate/models/yt.py
yt_concate/pipeline/__init__.py
yt_concate/pipeline/pipeline.py
yt_concate/pipeline/steps/__init__.py
yt_concate/pipeline/steps/download_captions.py
yt_concate/pipeline/steps/download_captions_concur_thread.py
yt_concate/pipeline/steps/download_captions_process.py
yt_concate/pipeline/steps/download_captions_thread.py
yt_concate/pipeline/steps/download_videos.py
yt_concate/pipeline/steps/download_videos_concur_thread.py
yt_concate/pipeline/steps/download_videos_process.py
yt_concate/pipeline/steps/download_videos_thread.py
yt_concate/pipeline/steps/edit_video.py
yt_concate/pipeline/steps/get_video_list.py
yt_concate/pipeline/steps/initialize_yt.py
yt_concate/pipeline/steps/postflight.py
yt_concate/pipeline/steps/preflight.py
yt_concate/pipeline/steps/read_caption.py
yt_concate/pipeline/steps/search.py
yt_concate/pipeline/steps/step.py
yt_concate_jason-0.1.1.dist-info/LICENSE
yt_concate_jason-0.1.1.dist-info/METADATA
yt_concate_jason-0.1.1.dist-info/WHEEL
yt_concate_jason-0.1.1.dist-info/top_level.txt
yt_concate_jason-0.1.1.dist-info/RECORD
