Metadata-Version: 2.1
Name: yt-concate-jason
Version: 0.1.1
Summary: Produce a concatenated video from clips that mentioned a word from a YouTube channel.
Home-page: https://github.com/wind50321/yt-concate
Author: Jason Chen
Author-email: jason@gmail.com
License: MIT
Platform: UNKNOWN
Classifier: License :: OSI Approved :: MIT License
Classifier: Programming Language :: Python
Classifier: Programming Language :: Python :: 3
Classifier: Programming Language :: Python :: 3.6
Classifier: Programming Language :: Python :: Implementation :: CPython
Classifier: Programming Language :: Python :: Implementation :: PyPy
Requires-Python: >=3.9.0
Requires-Dist: moviepy
Requires-Dist: python-dotenv
Requires-Dist: pytube
Requires-Dist: requests
Requires-Dist: urllib3
